mintii/__init__.py
mintii/router.py
mintii/tracker.py
mintii-0.1.1.dist-info/METADATA
mintii-0.1.1.dist-info/WHEEL
mintii-0.1.1.dist-info/RECORD
